setup.cfg
setup.py
godnames/__init__.py
godnames/command_line.py
godnames/godnames.py
godnames.egg-info/PKG-INFO
godnames.egg-info/SOURCES.txt
godnames.egg-info/dependency_links.txt
godnames.egg-info/entry_points.txt
godnames.egg-info/top_level.txt