Metadata-Version: 1.1
Name: godnames
Version: 1.1.1
Summary: A library to generate randomly names
Home-page: https://github.com/rphlo/py-godnames
Author: Raphael Stefanini
Author-email: rphl@rphl.net
License: UNKNOWN
Download-URL: https://github.com/rphlo/py-godnames/tarball/1.1.1
Keywords: random,naming,name
Platform: UNKNOWN
Classifier: Operating System :: OS Independent
Classifier: Programming Language :: Python
Classifier: Programming Language :: Python :: 2
Classifier: Programming Language :: Python :: 3
